{
  "lastUpdated": "2026-02-13T12:23:34.564Z",
  "agents": [
    {
      "id": "coderabbit",
      "name": "CodeRabbit",
      "color": "#f97316",
      "query": "commenter:coderabbitai[bot]",
      "stats": {
        "totalReviews": 2661464,
        "last7Days": 63716,
        "trend": 0
      }
    },
    {
      "id": "ellipsis",
      "name": "Ellipsis",
      "color": "#06b6d4",
      "query": "commenter:ellipsis-dev[bot]",
      "stats": {
        "totalReviews": 63348,
        "last7Days": 994,
        "trend": 0
      }
    },
    {
      "id": "sourcery",
      "name": "Sourcery",
      "color": "#ec4899",
      "query": "commenter:sourcery-ai[bot]",
      "stats": {
        "totalReviews": 475571,
        "last7Days": 7060,
        "trend": 0
      }
    },
    {
      "id": "greptile",
      "name": "Greptile",
      "color": "#22c55e",
      "query": "commenter:greptile-apps[bot]",
      "stats": {
        "totalReviews": 154175,
        "last7Days": 11213,
        "trend": 0
      }
    },
    {
      "id": "jules",
      "name": "Jules",
      "color": "#4285f4",
      "query": "commenter:google-labs-jules[bot]",
      "stats": {
        "totalReviews": 395116,
        "last7Days": 42330,
        "trend": 0
      }
    }
  ]
}