{
  "lastUpdated": "2026-02-13T00:47:02.546Z",
  "agents": [
    {
      "id": "coderabbit",
      "name": "CodeRabbit",
      "color": "#f97316",
      "query": "commenter:coderabbitai[bot]",
      "stats": {
        "totalReviews": 2657296,
        "last7Days": 58985,
        "trend": 0
      }
    },
    {
      "id": "ellipsis",
      "name": "Ellipsis",
      "color": "#06b6d4",
      "query": "commenter:ellipsis-dev[bot]",
      "stats": {
        "totalReviews": 63272,
        "last7Days": 889,
        "trend": 0
      }
    },
    {
      "id": "sourcery",
      "name": "Sourcery",
      "color": "#ec4899",
      "query": "commenter:sourcery-ai[bot]",
      "stats": {
        "totalReviews": 475004,
        "last7Days": 6657,
        "trend": 0
      }
    },
    {
      "id": "greptile",
      "name": "Greptile",
      "color": "#22c55e",
      "query": "commenter:greptile-apps[bot]",
      "stats": {
        "totalReviews": 153300,
        "last7Days": 10342,
        "trend": 0
      }
    },
    {
      "id": "jules",
      "name": "Jules",
      "color": "#4285f4",
      "query": "commenter:google-labs-jules[bot]",
      "stats": {
        "totalReviews": 392712,
        "last7Days": 39469,
        "trend": 0
      }
    }
  ]
}