{
  "lastUpdated": "2026-02-06T18:26:02.028Z",
  "agents": [
    {
      "id": "coderabbit",
      "name": "CodeRabbit",
      "color": "#f97316",
      "query": "commenter:coderabbitai[bot]",
      "stats": {
        "totalReviews": 2596775,
        "last7Days": 77956,
        "trend": 0
      }
    },
    {
      "id": "ellipsis",
      "name": "Ellipsis",
      "color": "#06b6d4",
      "query": "commenter:ellipsis-dev[bot]",
      "stats": {
        "totalReviews": 62315,
        "last7Days": 920,
        "trend": 0
      }
    },
    {
      "id": "sourcery",
      "name": "Sourcery",
      "color": "#ec4899",
      "query": "commenter:sourcery-ai[bot]",
      "stats": {
        "totalReviews": 469461,
        "last7Days": 5957,
        "trend": 0
      }
    },
    {
      "id": "greptile",
      "name": "Greptile",
      "color": "#22c55e",
      "query": "commenter:greptile-apps[bot]",
      "stats": {
        "totalReviews": 142401,
        "last7Days": 10793,
        "trend": 0
      }
    },
    {
      "id": "jules",
      "name": "Jules",
      "color": "#4285f4",
      "query": "commenter:google-labs-jules[bot]",
      "stats": {
        "totalReviews": 351360,
        "last7Days": 49463,
        "trend": 0
      }
    }
  ]
}