{
  "lastUpdated": "2026-02-03T18:29:45.270Z",
  "agents": [
    {
      "id": "coderabbit",
      "name": "CodeRabbit",
      "color": "#f97316",
      "query": "commenter:coderabbitai[bot]",
      "stats": {
        "totalReviews": 2562077,
        "last7Days": 80253,
        "trend": 0
      }
    },
    {
      "id": "ellipsis",
      "name": "Ellipsis",
      "color": "#06b6d4",
      "query": "commenter:ellipsis-dev[bot]",
      "stats": {
        "totalReviews": 61874,
        "last7Days": 998,
        "trend": 0
      }
    },
    {
      "id": "sourcery",
      "name": "Sourcery",
      "color": "#ec4899",
      "query": "commenter:sourcery-ai[bot]",
      "stats": {
        "totalReviews": 467103,
        "last7Days": 5435,
        "trend": 0
      }
    },
    {
      "id": "greptile",
      "name": "Greptile",
      "color": "#22c55e",
      "query": "commenter:greptile-apps[bot]",
      "stats": {
        "totalReviews": 137106,
        "last7Days": 9741,
        "trend": 0
      }
    },
    {
      "id": "jules",
      "name": "Jules",
      "color": "#4285f4",
      "query": "commenter:google-labs-jules[bot]",
      "stats": {
        "totalReviews": 330280,
        "last7Days": 46907,
        "trend": 0
      }
    }
  ]
}