{
  "lastUpdated": "2026-02-07T00:41:51.155Z",
  "agents": [
    {
      "id": "coderabbit",
      "name": "CodeRabbit",
      "color": "#f97316",
      "query": "commenter:coderabbitai[bot]",
      "stats": {
        "totalReviews": 2598386,
        "last7Days": 70942,
        "trend": 0
      }
    },
    {
      "id": "ellipsis",
      "name": "Ellipsis",
      "color": "#06b6d4",
      "query": "commenter:ellipsis-dev[bot]",
      "stats": {
        "totalReviews": 62392,
        "last7Days": 925,
        "trend": 0
      }
    },
    {
      "id": "sourcery",
      "name": "Sourcery",
      "color": "#ec4899",
      "query": "commenter:sourcery-ai[bot]",
      "stats": {
        "totalReviews": 469570,
        "last7Days": 5502,
        "trend": 0
      }
    },
    {
      "id": "greptile",
      "name": "Greptile",
      "color": "#22c55e",
      "query": "commenter:greptile-apps[bot]",
      "stats": {
        "totalReviews": 142867,
        "last7Days": 10066,
        "trend": 0
      }
    },
    {
      "id": "jules",
      "name": "Jules",
      "color": "#4285f4",
      "query": "commenter:google-labs-jules[bot]",
      "stats": {
        "totalReviews": 352902,
        "last7Days": 44369,
        "trend": 0
      }
    }
  ]
}